{
    "network": "Abilene",
    "traffic_matrix": 5,
    "config": {
        "n_particles": 200,
        "dimensions": 30,
        "options": {
            "c1": 2.25,
            "c2": 1.75,
            "w": 0.7,
            "k": 100,
            "p": 1
        },
        "iterations": 1200,
        "runs": 5,
        "threads": 6
    },
    "results": [
        {
            "run": 1,
            "best_cost": null,
            "best_pos": [
                1,
                0,
                0,
                1,
                1,
                1,
                0,
                1,
                1,
                0,
                0,
                0,
                0,
                1,
                1,
                1,
                0,
                1,
                1,
                0,
                0,
                1,
                1,
                1,
                0,
                0,
                1,
                0,
                1,
                1
            ],
            "cost_history": {
                "mode": "compressed",
                "step": 100,
                "remove_consecutive_duplicates": false,
                "inf_strategy": "null",
                "data": [
                    {
                        "iter": 1,
                        "cost": null
                    },
                    {
                        "iter": 101,
                        "cost": null
                    },
                    {
                        "iter": 201,
                        "cost": null
                    },
                    {
                        "iter": 301,
                        "cost": null
                    },
                    {
                        "iter": 401,
                        "cost": null
                    },
                    {
                        "iter": 501,
                        "cost": null
                    },
                    {
                        "iter": 601,
                        "cost": null
                    },
                    {
                        "iter": 701,
                        "cost": null
                    },
                    {
                        "iter": 801,
                        "cost": null
                    },
                    {
                        "iter": 901,
                        "cost": null
                    },
                    {
                        "iter": 1001,
                        "cost": null
                    },
                    {
                        "iter": 1101,
                        "cost": null
                    }
                ]
            }
        },
        {
            "run": 2,
            "best_cost": 91.5168794405588,
            "best_pos": [
                1,
                1,
                1,
                1,
                1,
                1,
                0,
                0,
                1,
                1,
                1,
                0,
                1,
                1,
                0,
                1,
                1,
                0,
                0,
                1,
                0,
                1,
                1,
                0,
                1,
                0,
                0,
                1,
                1,
                1
            ],
            "cost_history": {
                "mode": "compressed",
                "step": 100,
                "remove_consecutive_duplicates": false,
                "inf_strategy": "null",
                "data": [
                    {
                        "iter": 1,
                        "cost": null
                    },
                    {
                        "iter": 101,
                        "cost": null
                    },
                    {
                        "iter": 201,
                        "cost": null
                    },
                    {
                        "iter": 301,
                        "cost": 91.5888711221572
                    },
                    {
                        "iter": 401,
                        "cost": 91.5888711221572
                    },
                    {
                        "iter": 501,
                        "cost": 91.5888711221572
                    },
                    {
                        "iter": 601,
                        "cost": 91.5888711221572
                    },
                    {
                        "iter": 701,
                        "cost": 91.5888711221572
                    },
                    {
                        "iter": 801,
                        "cost": 91.5888711221572
                    },
                    {
                        "iter": 901,
                        "cost": 91.5888711221572
                    },
                    {
                        "iter": 1001,
                        "cost": 91.5168794405588
                    },
                    {
                        "iter": 1101,
                        "cost": 91.5168794405588
                    }
                ]
            }
        },
        {
            "run": 3,
            "best_cost": 94.25941377286452,
            "best_pos": [
                1,
                1,
                1,
                1,
                1,
                1,
                1,
                0,
                1,
                0,
                1,
                0,
                1,
                1,
                1,
                1,
                1,
                0,
                0,
                1,
                0,
                0,
                1,
                0,
                1,
                1,
                0,
                1,
                1,
                1
            ],
            "cost_history": {
                "mode": "compressed",
                "step": 100,
                "remove_consecutive_duplicates": false,
                "inf_strategy": "null",
                "data": [
                    {
                        "iter": 1,
                        "cost": null
                    },
                    {
                        "iter": 101,
                        "cost": null
                    },
                    {
                        "iter": 201,
                        "cost": null
                    },
                    {
                        "iter": 301,
                        "cost": null
                    },
                    {
                        "iter": 401,
                        "cost": null
                    },
                    {
                        "iter": 501,
                        "cost": null
                    },
                    {
                        "iter": 601,
                        "cost": 100.48908563623432
                    },
                    {
                        "iter": 701,
                        "cost": 100.48908563623432
                    },
                    {
                        "iter": 801,
                        "cost": 99.32192859836611
                    },
                    {
                        "iter": 901,
                        "cost": 96.45655661818071
                    },
                    {
                        "iter": 1001,
                        "cost": 94.37493055604442
                    },
                    {
                        "iter": 1101,
                        "cost": 94.25941377286452
                    }
                ]
            }
        },
        {
            "run": 4,
            "best_cost": 92.03134164505956,
            "best_pos": [
                1,
                1,
                1,
                1,
                1,
                1,
                0,
                0,
                0,
                1,
                1,
                0,
                1,
                1,
                1,
                1,
                1,
                0,
                1,
                1,
                0,
                0,
                1,
                0,
                1,
                0,
                0,
                1,
                1,
                1
            ],
            "cost_history": {
                "mode": "compressed",
                "step": 100,
                "remove_consecutive_duplicates": false,
                "inf_strategy": "null",
                "data": [
                    {
                        "iter": 1,
                        "cost": null
                    },
                    {
                        "iter": 101,
                        "cost": null
                    },
                    {
                        "iter": 201,
                        "cost": null
                    },
                    {
                        "iter": 301,
                        "cost": null
                    },
                    {
                        "iter": 401,
                        "cost": null
                    },
                    {
                        "iter": 501,
                        "cost": null
                    },
                    {
                        "iter": 601,
                        "cost": null
                    },
                    {
                        "iter": 701,
                        "cost": null
                    },
                    {
                        "iter": 801,
                        "cost": null
                    },
                    {
                        "iter": 901,
                        "cost": null
                    },
                    {
                        "iter": 1001,
                        "cost": 112.36739018381527
                    },
                    {
                        "iter": 1101,
                        "cost": 92.03134164505956
                    }
                ]
            }
        },
        {
            "run": 5,
            "best_cost": null,
            "best_pos": [
                0,
                1,
                0,
                0,
                0,
                1,
                0,
                0,
                1,
                1,
                0,
                0,
                0,
                1,
                0,
                0,
                0,
                1,
                0,
                0,
                1,
                1,
                1,
                1,
                0,
                0,
                0,
                1,
                0,
                1
            ],
            "cost_history": {
                "mode": "compressed",
                "step": 100,
                "remove_consecutive_duplicates": false,
                "inf_strategy": "null",
                "data": [
                    {
                        "iter": 1,
                        "cost": null
                    },
                    {
                        "iter": 101,
                        "cost": null
                    },
                    {
                        "iter": 201,
                        "cost": null
                    },
                    {
                        "iter": 301,
                        "cost": null
                    },
                    {
                        "iter": 401,
                        "cost": null
                    },
                    {
                        "iter": 501,
                        "cost": null
                    },
                    {
                        "iter": 601,
                        "cost": null
                    },
                    {
                        "iter": 701,
                        "cost": null
                    },
                    {
                        "iter": 801,
                        "cost": null
                    },
                    {
                        "iter": 901,
                        "cost": null
                    },
                    {
                        "iter": 1001,
                        "cost": null
                    },
                    {
                        "iter": 1101,
                        "cost": null
                    }
                ]
            }
        }
    ]
}