{
    "network": "Abilene",
    "traffic_matrix": 5,
    "config": {
        "n_particles": 200,
        "dimensions": 30,
        "options": {
            "c1": 1.5,
            "c2": 2.5,
            "w": 0.7,
            "k": 100,
            "p": 1
        },
        "iterations": 1100,
        "runs": 20,
        "threads": 6
    },
    "results": [
        {
            "run": 1,
            "best_cost": null,
            "best_pos": [
                0,
                1,
                0,
                1,
                0,
                1,
                0,
                1,
                1,
                0,
                0,
                1,
                0,
                0,
                0,
                0,
                0,
                0,
                0,
                0,
                1,
                0,
                0,
                0,
                1,
                0,
                0,
                0,
                0,
                1
            ],
            "cost_history": {
                "mode": "compressed",
                "step": 100,
                "remove_consecutive_duplicates": false,
                "inf_strategy": "null",
                "data": [
                    {
                        "iter": 1,
                        "cost": null
                    },
                    {
                        "iter": 101,
                        "cost": null
                    },
                    {
                        "iter": 201,
                        "cost": null
                    },
                    {
                        "iter": 301,
                        "cost": null
                    },
                    {
                        "iter": 401,
                        "cost": null
                    },
                    {
                        "iter": 501,
                        "cost": null
                    },
                    {
                        "iter": 601,
                        "cost": null
                    },
                    {
                        "iter": 701,
                        "cost": null
                    },
                    {
                        "iter": 801,
                        "cost": null
                    },
                    {
                        "iter": 901,
                        "cost": null
                    },
                    {
                        "iter": 1001,
                        "cost": null
                    }
                ]
            }
        },
        {
            "run": 2,
            "best_cost": 94.93265816421444,
            "best_pos": [
                1,
                1,
                1,
                0,
                1,
                1,
                1,
                1,
                0,
                1,
                0,
                1,
                0,
                1,
                1,
                0,
                1,
                1,
                1,
                1,
                0,
                1,
                0,
                0,
                1,
                0,
                0,
                1,
                1,
                1
            ],
            "cost_history": {
                "mode": "compressed",
                "step": 100,
                "remove_consecutive_duplicates": false,
                "inf_strategy": "null",
                "data": [
                    {
                        "iter": 1,
                        "cost": null
                    },
                    {
                        "iter": 101,
                        "cost": null
                    },
                    {
                        "iter": 201,
                        "cost": null
                    },
                    {
                        "iter": 301,
                        "cost": null
                    },
                    {
                        "iter": 401,
                        "cost": null
                    },
                    {
                        "iter": 501,
                        "cost": 108.65834196468411
                    },
                    {
                        "iter": 601,
                        "cost": 104.51821320274438
                    },
                    {
                        "iter": 701,
                        "cost": 101.1112406002721
                    },
                    {
                        "iter": 801,
                        "cost": 101.1112406002721
                    },
                    {
                        "iter": 901,
                        "cost": 100.95185124673759
                    },
                    {
                        "iter": 1001,
                        "cost": 94.93265816421444
                    }
                ]
            }
        },
        {
            "run": 3,
            "best_cost": 90.32283975391668,
            "best_pos": [
                1,
                1,
                1,
                0,
                1,
                1,
                1,
                0,
                0,
                1,
                0,
                1,
                1,
                1,
                1,
                0,
                1,
                0,
                1,
                1,
                0,
                1,
                0,
                0,
                1,
                1,
                1,
                1,
                1,
                1
            ],
            "cost_history": {
                "mode": "compressed",
                "step": 100,
                "remove_consecutive_duplicates": false,
                "inf_strategy": "null",
                "data": [
                    {
                        "iter": 1,
                        "cost": null
                    },
                    {
                        "iter": 101,
                        "cost": null
                    },
                    {
                        "iter": 201,
                        "cost": null
                    },
                    {
                        "iter": 301,
                        "cost": null
                    },
                    {
                        "iter": 401,
                        "cost": null
                    },
                    {
                        "iter": 501,
                        "cost": null
                    },
                    {
                        "iter": 601,
                        "cost": null
                    },
                    {
                        "iter": 701,
                        "cost": 102.27513412414311
                    },
                    {
                        "iter": 801,
                        "cost": 95.28935682343153
                    },
                    {
                        "iter": 901,
                        "cost": 90.32283975391668
                    },
                    {
                        "iter": 1001,
                        "cost": 90.32283975391668
                    }
                ]
            }
        },
        {
            "run": 4,
            "best_cost": 90.05997603161411,
            "best_pos": [
                1,
                1,
                1,
                0,
                1,
                1,
                1,
                1,
                0,
                0,
                0,
                1,
                1,
                1,
                1,
                0,
                1,
                0,
                1,
                1,
                1,
                1,
                0,
                0,
                1,
                1,
                0,
                1,
                1,
                1
            ],
            "cost_history": {
                "mode": "compressed",
                "step": 100,
                "remove_consecutive_duplicates": false,
                "inf_strategy": "null",
                "data": [
                    {
                        "iter": 1,
                        "cost": null
                    },
                    {
                        "iter": 101,
                        "cost": null
                    },
                    {
                        "iter": 201,
                        "cost": null
                    },
                    {
                        "iter": 301,
                        "cost": null
                    },
                    {
                        "iter": 401,
                        "cost": null
                    },
                    {
                        "iter": 501,
                        "cost": null
                    },
                    {
                        "iter": 601,
                        "cost": null
                    },
                    {
                        "iter": 701,
                        "cost": 107.21302416662195
                    },
                    {
                        "iter": 801,
                        "cost": 90.05997603161411
                    },
                    {
                        "iter": 901,
                        "cost": 90.05997603161411
                    },
                    {
                        "iter": 1001,
                        "cost": 90.05997603161411
                    }
                ]
            }
        },
        {
            "run": 5,
            "best_cost": 86.58026501040148,
            "best_pos": [
                1,
                1,
                1,
                0,
                1,
                1,
                1,
                0,
                0,
                1,
                0,
                1,
                1,
                1,
                1,
                0,
                1,
                0,
                1,
                1,
                0,
                1,
                0,
                0,
                1,
                1,
                0,
                1,
                1,
                1
            ],
            "cost_history": {
                "mode": "compressed",
                "step": 100,
                "remove_consecutive_duplicates": false,
                "inf_strategy": "null",
                "data": [
                    {
                        "iter": 1,
                        "cost": null
                    },
                    {
                        "iter": 101,
                        "cost": null
                    },
                    {
                        "iter": 201,
                        "cost": null
                    },
                    {
                        "iter": 301,
                        "cost": null
                    },
                    {
                        "iter": 401,
                        "cost": 102.78173148578783
                    },
                    {
                        "iter": 501,
                        "cost": 99.07458497318004
                    },
                    {
                        "iter": 601,
                        "cost": 90.13094362949543
                    },
                    {
                        "iter": 701,
                        "cost": 90.13094362949543
                    },
                    {
                        "iter": 801,
                        "cost": 90.13094362949543
                    },
                    {
                        "iter": 901,
                        "cost": 86.58026501040148
                    },
                    {
                        "iter": 1001,
                        "cost": 86.58026501040148
                    }
                ]
            }
        },
        {
            "run": 6,
            "best_cost": null,
            "best_pos": [
                1,
                1,
                0,
                0,
                0,
                0,
                1,
                0,
                1,
                1,
                0,
                1,
                0,
                0,
                0,
                1,
                0,
                1,
                0,
                1,
                0,
                0,
                0,
                0,
                1,
                0,
                1,
                1,
                1,
                1
            ],
            "cost_history": {
                "mode": "compressed",
                "step": 100,
                "remove_consecutive_duplicates": false,
                "inf_strategy": "null",
                "data": [
                    {
                        "iter": 1,
                        "cost": null
                    },
                    {
                        "iter": 101,
                        "cost": null
                    },
                    {
                        "iter": 201,
                        "cost": null
                    },
                    {
                        "iter": 301,
                        "cost": null
                    },
                    {
                        "iter": 401,
                        "cost": null
                    },
                    {
                        "iter": 501,
                        "cost": null
                    },
                    {
                        "iter": 601,
                        "cost": null
                    },
                    {
                        "iter": 701,
                        "cost": null
                    },
                    {
                        "iter": 801,
                        "cost": null
                    },
                    {
                        "iter": 901,
                        "cost": null
                    },
                    {
                        "iter": 1001,
                        "cost": null
                    }
                ]
            }
        },
        {
            "run": 7,
            "best_cost": null,
            "best_pos": [
                1,
                1,
                0,
                0,
                0,
                0,
                1,
                1,
                0,
                1,
                1,
                1,
                0,
                0,
                0,
                1,
                0,
                0,
                0,
                1,
                1,
                0,
                0,
                0,
                1,
                0,
                0,
                1,
                0,
                1
            ],
            "cost_history": {
                "mode": "compressed",
                "step": 100,
                "remove_consecutive_duplicates": false,
                "inf_strategy": "null",
                "data": [
                    {
                        "iter": 1,
                        "cost": null
                    },
                    {
                        "iter": 101,
                        "cost": null
                    },
                    {
                        "iter": 201,
                        "cost": null
                    },
                    {
                        "iter": 301,
                        "cost": null
                    },
                    {
                        "iter": 401,
                        "cost": null
                    },
                    {
                        "iter": 501,
                        "cost": null
                    },
                    {
                        "iter": 601,
                        "cost": null
                    },
                    {
                        "iter": 701,
                        "cost": null
                    },
                    {
                        "iter": 801,
                        "cost": null
                    },
                    {
                        "iter": 901,
                        "cost": null
                    },
                    {
                        "iter": 1001,
                        "cost": null
                    }
                ]
            }
        },
        {
            "run": 8,
            "best_cost": 104.30707012867882,
            "best_pos": [
                1,
                1,
                1,
                1,
                1,
                1,
                1,
                1,
                0,
                1,
                1,
                1,
                1,
                1,
                1,
                0,
                1,
                0,
                1,
                0,
                1,
                1,
                0,
                1,
                0,
                0,
                1,
                0,
                1,
                1
            ],
            "cost_history": {
                "mode": "compressed",
                "step": 100,
                "remove_consecutive_duplicates": false,
                "inf_strategy": "null",
                "data": [
                    {
                        "iter": 1,
                        "cost": null
                    },
                    {
                        "iter": 101,
                        "cost": null
                    },
                    {
                        "iter": 201,
                        "cost": null
                    },
                    {
                        "iter": 301,
                        "cost": null
                    },
                    {
                        "iter": 401,
                        "cost": null
                    },
                    {
                        "iter": 501,
                        "cost": null
                    },
                    {
                        "iter": 601,
                        "cost": null
                    },
                    {
                        "iter": 701,
                        "cost": null
                    },
                    {
                        "iter": 801,
                        "cost": null
                    },
                    {
                        "iter": 901,
                        "cost": null
                    },
                    {
                        "iter": 1001,
                        "cost": null
                    }
                ]
            }
        },
        {
            "run": 9,
            "best_cost": 97.24446685183403,
            "best_pos": [
                1,
                1,
                0,
                1,
                1,
                1,
                1,
                1,
                0,
                1,
                1,
                0,
                1,
                0,
                1,
                1,
                1,
                1,
                1,
                1,
                0,
                1,
                0,
                0,
                1,
                0,
                1,
                1,
                1,
                1
            ],
            "cost_history": {
                "mode": "compressed",
                "step": 100,
                "remove_consecutive_duplicates": false,
                "inf_strategy": "null",
                "data": [
                    {
                        "iter": 1,
                        "cost": null
                    },
                    {
                        "iter": 101,
                        "cost": null
                    },
                    {
                        "iter": 201,
                        "cost": null
                    },
                    {
                        "iter": 301,
                        "cost": null
                    },
                    {
                        "iter": 401,
                        "cost": null
                    },
                    {
                        "iter": 501,
                        "cost": null
                    },
                    {
                        "iter": 601,
                        "cost": null
                    },
                    {
                        "iter": 701,
                        "cost": null
                    },
                    {
                        "iter": 801,
                        "cost": 113.04750933352895
                    },
                    {
                        "iter": 901,
                        "cost": 97.24446685183403
                    },
                    {
                        "iter": 1001,
                        "cost": 97.24446685183403
                    }
                ]
            }
        },
        {
            "run": 10,
            "best_cost": 96.93813569791384,
            "best_pos": [
                1,
                1,
                0,
                1,
                1,
                1,
                1,
                1,
                0,
                1,
                1,
                0,
                1,
                0,
                1,
                1,
                1,
                1,
                1,
                1,
                1,
                1,
                0,
                0,
                0,
                1,
                1,
                0,
                1,
                1
            ],
            "cost_history": {
                "mode": "compressed",
                "step": 100,
                "remove_consecutive_duplicates": false,
                "inf_strategy": "null",
                "data": [
                    {
                        "iter": 1,
                        "cost": null
                    },
                    {
                        "iter": 101,
                        "cost": null
                    },
                    {
                        "iter": 201,
                        "cost": 108.1397677643959
                    },
                    {
                        "iter": 301,
                        "cost": 103.63249615945693
                    },
                    {
                        "iter": 401,
                        "cost": 103.63249615945693
                    },
                    {
                        "iter": 501,
                        "cost": 103.63249615945693
                    },
                    {
                        "iter": 601,
                        "cost": 96.93813569791384
                    },
                    {
                        "iter": 701,
                        "cost": 96.93813569791384
                    },
                    {
                        "iter": 801,
                        "cost": 96.93813569791384
                    },
                    {
                        "iter": 901,
                        "cost": 96.93813569791384
                    },
                    {
                        "iter": 1001,
                        "cost": 96.93813569791384
                    }
                ]
            }
        },
        {
            "run": 11,
            "best_cost": 107.83529406647129,
            "best_pos": [
                1,
                1,
                1,
                1,
                1,
                1,
                1,
                1,
                1,
                0,
                1,
                1,
                1,
                1,
                1,
                1,
                1,
                0,
                1,
                1,
                0,
                1,
                0,
                1,
                0,
                1,
                0,
                1,
                1,
                1
            ],
            "cost_history": {
                "mode": "compressed",
                "step": 100,
                "remove_consecutive_duplicates": false,
                "inf_strategy": "null",
                "data": [
                    {
                        "iter": 1,
                        "cost": null
                    },
                    {
                        "iter": 101,
                        "cost": null
                    },
                    {
                        "iter": 201,
                        "cost": null
                    },
                    {
                        "iter": 301,
                        "cost": null
                    },
                    {
                        "iter": 401,
                        "cost": null
                    },
                    {
                        "iter": 501,
                        "cost": null
                    },
                    {
                        "iter": 601,
                        "cost": null
                    },
                    {
                        "iter": 701,
                        "cost": null
                    },
                    {
                        "iter": 801,
                        "cost": null
                    },
                    {
                        "iter": 901,
                        "cost": 107.83529406647129
                    },
                    {
                        "iter": 1001,
                        "cost": 107.83529406647129
                    }
                ]
            }
        },
        {
            "run": 12,
            "best_cost": 85.27642868637679,
            "best_pos": [
                1,
                1,
                1,
                0,
                1,
                1,
                1,
                0,
                0,
                1,
                0,
                1,
                1,
                1,
                1,
                0,
                1,
                0,
                1,
                1,
                0,
                1,
                0,
                0,
                1,
                0,
                0,
                1,
                1,
                1
            ],
            "cost_history": {
                "mode": "compressed",
                "step": 100,
                "remove_consecutive_duplicates": false,
                "inf_strategy": "null",
                "data": [
                    {
                        "iter": 1,
                        "cost": null
                    },
                    {
                        "iter": 101,
                        "cost": 93.87235326198345
                    },
                    {
                        "iter": 201,
                        "cost": 93.87235326198345
                    },
                    {
                        "iter": 301,
                        "cost": 93.82870752474481
                    },
                    {
                        "iter": 401,
                        "cost": 92.52487120072013
                    },
                    {
                        "iter": 501,
                        "cost": 92.52487120072013
                    },
                    {
                        "iter": 601,
                        "cost": 92.52487120072013
                    },
                    {
                        "iter": 701,
                        "cost": 92.52487120072013
                    },
                    {
                        "iter": 801,
                        "cost": 85.27642868637679
                    },
                    {
                        "iter": 901,
                        "cost": 85.27642868637679
                    },
                    {
                        "iter": 1001,
                        "cost": 85.27642868637679
                    }
                ]
            }
        },
        {
            "run": 13,
            "best_cost": 103.10858814063094,
            "best_pos": [
                1,
                1,
                0,
                1,
                1,
                1,
                1,
                1,
                1,
                1,
                1,
                0,
                0,
                0,
                1,
                1,
                1,
                1,
                1,
                1,
                0,
                1,
                0,
                0,
                1,
                0,
                1,
                1,
                1,
                1
            ],
            "cost_history": {
                "mode": "compressed",
                "step": 100,
                "remove_consecutive_duplicates": false,
                "inf_strategy": "null",
                "data": [
                    {
                        "iter": 1,
                        "cost": null
                    },
                    {
                        "iter": 101,
                        "cost": null
                    },
                    {
                        "iter": 201,
                        "cost": null
                    },
                    {
                        "iter": 301,
                        "cost": null
                    },
                    {
                        "iter": 401,
                        "cost": null
                    },
                    {
                        "iter": 501,
                        "cost": null
                    },
                    {
                        "iter": 601,
                        "cost": null
                    },
                    {
                        "iter": 701,
                        "cost": null
                    },
                    {
                        "iter": 801,
                        "cost": null
                    },
                    {
                        "iter": 901,
                        "cost": 106.03929797945477
                    },
                    {
                        "iter": 1001,
                        "cost": 106.03929797945477
                    }
                ]
            }
        },
        {
            "run": 14,
            "best_cost": null,
            "best_pos": [
                0,
                1,
                0,
                0,
                1,
                0,
                0,
                0,
                1,
                0,
                0,
                1,
                0,
                1,
                1,
                0,
                0,
                0,
                0,
                0,
                0,
                0,
                1,
                0,
                1,
                0,
                0,
                0,
                1,
                1
            ],
            "cost_history": {
                "mode": "compressed",
                "step": 100,
                "remove_consecutive_duplicates": false,
                "inf_strategy": "null",
                "data": [
                    {
                        "iter": 1,
                        "cost": null
                    },
                    {
                        "iter": 101,
                        "cost": null
                    },
                    {
                        "iter": 201,
                        "cost": null
                    },
                    {
                        "iter": 301,
                        "cost": null
                    },
                    {
                        "iter": 401,
                        "cost": null
                    },
                    {
                        "iter": 501,
                        "cost": null
                    },
                    {
                        "iter": 601,
                        "cost": null
                    },
                    {
                        "iter": 701,
                        "cost": null
                    },
                    {
                        "iter": 801,
                        "cost": null
                    },
                    {
                        "iter": 901,
                        "cost": null
                    },
                    {
                        "iter": 1001,
                        "cost": null
                    }
                ]
            }
        },
        {
            "run": 15,
            "best_cost": null,
            "best_pos": [
                0,
                1,
                0,
                0,
                1,
                0,
                1,
                1,
                0,
                0,
                0,
                1,
                1,
                0,
                1,
                0,
                0,
                0,
                0,
                0,
                0,
                1,
                0,
                1,
                1,
                1,
                1,
                1,
                0,
                1
            ],
            "cost_history": {
                "mode": "compressed",
                "step": 100,
                "remove_consecutive_duplicates": false,
                "inf_strategy": "null",
                "data": [
                    {
                        "iter": 1,
                        "cost": null
                    },
                    {
                        "iter": 101,
                        "cost": null
                    },
                    {
                        "iter": 201,
                        "cost": null
                    },
                    {
                        "iter": 301,
                        "cost": null
                    },
                    {
                        "iter": 401,
                        "cost": null
                    },
                    {
                        "iter": 501,
                        "cost": null
                    },
                    {
                        "iter": 601,
                        "cost": null
                    },
                    {
                        "iter": 701,
                        "cost": null
                    },
                    {
                        "iter": 801,
                        "cost": null
                    },
                    {
                        "iter": 901,
                        "cost": null
                    },
                    {
                        "iter": 1001,
                        "cost": null
                    }
                ]
            }
        },
        {
            "run": 16,
            "best_cost": null,
            "best_pos": [
                0,
                0,
                0,
                1,
                1,
                1,
                0,
                1,
                1,
                0,
                1,
                1,
                1,
                1,
                1,
                0,
                0,
                0,
                1,
                0,
                0,
                0,
                0,
                1,
                1,
                1,
                1,
                0,
                1,
                0
            ],
            "cost_history": {
                "mode": "compressed",
                "step": 100,
                "remove_consecutive_duplicates": false,
                "inf_strategy": "null",
                "data": [
                    {
                        "iter": 1,
                        "cost": null
                    },
                    {
                        "iter": 101,
                        "cost": null
                    },
                    {
                        "iter": 201,
                        "cost": null
                    },
                    {
                        "iter": 301,
                        "cost": null
                    },
                    {
                        "iter": 401,
                        "cost": null
                    },
                    {
                        "iter": 501,
                        "cost": null
                    },
                    {
                        "iter": 601,
                        "cost": null
                    },
                    {
                        "iter": 701,
                        "cost": null
                    },
                    {
                        "iter": 801,
                        "cost": null
                    },
                    {
                        "iter": 901,
                        "cost": null
                    },
                    {
                        "iter": 1001,
                        "cost": null
                    }
                ]
            }
        },
        {
            "run": 17,
            "best_cost": null,
            "best_pos": [
                1,
                1,
                1,
                1,
                1,
                0,
                0,
                0,
                0,
                0,
                1,
                1,
                0,
                0,
                0,
                0,
                0,
                0,
                0,
                0,
                1,
                1,
                1,
                0,
                1,
                1,
                1,
                1,
                0,
                0
            ],
            "cost_history": {
                "mode": "compressed",
                "step": 100,
                "remove_consecutive_duplicates": false,
                "inf_strategy": "null",
                "data": [
                    {
                        "iter": 1,
                        "cost": null
                    },
                    {
                        "iter": 101,
                        "cost": null
                    },
                    {
                        "iter": 201,
                        "cost": null
                    },
                    {
                        "iter": 301,
                        "cost": null
                    },
                    {
                        "iter": 401,
                        "cost": null
                    },
                    {
                        "iter": 501,
                        "cost": null
                    },
                    {
                        "iter": 601,
                        "cost": null
                    },
                    {
                        "iter": 701,
                        "cost": null
                    },
                    {
                        "iter": 801,
                        "cost": null
                    },
                    {
                        "iter": 901,
                        "cost": null
                    },
                    {
                        "iter": 1001,
                        "cost": null
                    }
                ]
            }
        },
        {
            "run": 18,
            "best_cost": 85.27642868637679,
            "best_pos": [
                1,
                1,
                1,
                0,
                1,
                1,
                1,
                0,
                0,
                1,
                0,
                1,
                1,
                1,
                1,
                0,
                1,
                0,
                1,
                1,
                0,
                1,
                0,
                0,
                1,
                0,
                0,
                1,
                1,
                1
            ],
            "cost_history": {
                "mode": "compressed",
                "step": 100,
                "remove_consecutive_duplicates": false,
                "inf_strategy": "null",
                "data": [
                    {
                        "iter": 1,
                        "cost": null
                    },
                    {
                        "iter": 101,
                        "cost": 106.36068956530005
                    },
                    {
                        "iter": 201,
                        "cost": 96.43866067151934
                    },
                    {
                        "iter": 301,
                        "cost": 91.23994191498464
                    },
                    {
                        "iter": 401,
                        "cost": 91.23994191498464
                    },
                    {
                        "iter": 501,
                        "cost": 87.83499490371739
                    },
                    {
                        "iter": 601,
                        "cost": 87.83499490371739
                    },
                    {
                        "iter": 701,
                        "cost": 87.83499490371739
                    },
                    {
                        "iter": 801,
                        "cost": 87.83499490371739
                    },
                    {
                        "iter": 901,
                        "cost": 85.27642868637679
                    },
                    {
                        "iter": 1001,
                        "cost": 85.27642868637679
                    }
                ]
            }
        },
        {
            "run": 19,
            "best_cost": 97.11410344480677,
            "best_pos": [
                1,
                1,
                0,
                1,
                1,
                1,
                1,
                1,
                0,
                0,
                1,
                0,
                1,
                0,
                1,
                1,
                1,
                1,
                1,
                1,
                1,
                1,
                0,
                0,
                1,
                1,
                1,
                1,
                1,
                1
            ],
            "cost_history": {
                "mode": "compressed",
                "step": 100,
                "remove_consecutive_duplicates": false,
                "inf_strategy": "null",
                "data": [
                    {
                        "iter": 1,
                        "cost": null
                    },
                    {
                        "iter": 101,
                        "cost": null
                    },
                    {
                        "iter": 201,
                        "cost": null
                    },
                    {
                        "iter": 301,
                        "cost": null
                    },
                    {
                        "iter": 401,
                        "cost": null
                    },
                    {
                        "iter": 501,
                        "cost": null
                    },
                    {
                        "iter": 601,
                        "cost": 99.43120658527572
                    },
                    {
                        "iter": 701,
                        "cost": 99.18723873885158
                    },
                    {
                        "iter": 801,
                        "cost": 97.11410344480677
                    },
                    {
                        "iter": 901,
                        "cost": 97.11410344480677
                    },
                    {
                        "iter": 1001,
                        "cost": 97.11410344480677
                    }
                ]
            }
        },
        {
            "run": 20,
            "best_cost": null,
            "best_pos": [
                0,
                1,
                0,
                0,
                0,
                1,
                1,
                1,
                0,
                1,
                1,
                0,
                0,
                1,
                1,
                1,
                0,
                1,
                1,
                0,
                1,
                0,
                0,
                0,
                1,
                1,
                1,
                1,
                0,
                0
            ],
            "cost_history": {
                "mode": "compressed",
                "step": 100,
                "remove_consecutive_duplicates": false,
                "inf_strategy": "null",
                "data": [
                    {
                        "iter": 1,
                        "cost": null
                    },
                    {
                        "iter": 101,
                        "cost": null
                    },
                    {
                        "iter": 201,
                        "cost": null
                    },
                    {
                        "iter": 301,
                        "cost": null
                    },
                    {
                        "iter": 401,
                        "cost": null
                    },
                    {
                        "iter": 501,
                        "cost": null
                    },
                    {
                        "iter": 601,
                        "cost": null
                    },
                    {
                        "iter": 701,
                        "cost": null
                    },
                    {
                        "iter": 801,
                        "cost": null
                    },
                    {
                        "iter": 901,
                        "cost": null
                    },
                    {
                        "iter": 1001,
                        "cost": null
                    }
                ]
            }
        }
    ]
}